README.md
pyproject.toml
setup.cfg
setup.py
kien/__init__.py
kien/commands.py
kien/error.py
kien/events.py
kien/runner.py
kien/transformation.py
kien/utils.py
kien/validation.py
kien.egg-info/PKG-INFO
kien.egg-info/SOURCES.txt
kien.egg-info/dependency_links.txt
kien.egg-info/requires.txt
kien.egg-info/top_level.txt
kien/command/__init__.py
kien/command/help.py
kien/command/quit.py
kien/command/set.py
kien/console/__init__.py
kien/console/interfaces.py
tests/__init__.py