Metadata-Version: 2.1
Name: kien
Version: 0.16.2
Summary: kien is a line-based command parser for creating shell-like interfaces
Home-page: https://github.com/silicann/kien
Author: Konrad Mohrfeldt
Author-email: mohrfeldt@silicann.com
License: GPLv3+
Platform: UNKNOWN
Classifier: Development Status :: 4 - Beta
Classifier: License :: OSI Approved :: GNU General Public License v3 or later (GPLv3+)
Classifier: Programming Language :: Python
Classifier: Programming Language :: Python :: 3
